{"id":78101020,"bedrooms":3,"numberOfImages":1,"numberOfFloorplans":1,"numberOfVirtualTours":0,"summary":"A three bedroom ground floor, purpose built flat in an excellent location just off Clapham High Street. The property has both a flexible layout and an eat in kitchen, also benefitting from being offered chain free.","displayAddress":"Triangle Place, Clapham","countryCode":"GB","location":{"latitude":51.461584,"longitude":-0.134149},"propertySubType":"Flat","listingUpdate":{"listingUpdateReason":"price_reduced","listingUpdateDate":"2020-05-22T09:24:10Z"},"premiumListing":false,"featuredProperty":false,"price":{"amount":449000,"frequency":"not specified","currencyCode":"GBP","displayPrices":[{"displayPrice":"£449,000","displayPriceQualifier":""}]},"customer":{"branchId":78413,"brandPlusLogoURI":"/brand/brand_rmchoice_logo_39479_0009.jpeg","contactTelephone":"020 8675 2224","branchDisplayName":"Dexters, Clapham","branchName":"Clapham","brandTradingName":"Dexters","branchLandingPageUrl":"/estate-agents/agent/Dexters/Clapham-78413.html","development":false,"showReducedProperties":true,"commercial":false,"showOnMap":true,"brandPlusLogoUrl":"https://media.rightmove.co.uk:443/dir/brand/brand_rmchoice_logo_39479_0009_max_100x50.jpeg"},"distance":null,"transactionType":"buy","productLabel":{"productLabelText":""},"commercial":false,"development":false,"residential":true,"students":false,"auction":false,"feesApply":false,"feesApplyText":null,"displaySize":"","showOnMap":true,"propertyUrl":"/property-for-sale/property-78101020.html","contactUrl":"/property-for-sale/contactBranch.html?propertyId=78101020","channel":"BUY","firstVisibleDate":"2020-03-10T16:27:43Z","keywords":[],"keywordMatchType":"no_keyword","saved":null,"hidden":null,"onlineViewingsAvailable":false,"propertyTypeFullDescription":"3 bedroom flat for sale","displayStatus":"","formattedBranchName":" by Dexters, Clapham","addedOrReduced":"Reduced on 22/05/2020","isRecent":false,"formattedDistance":"","heading":"","hasBrandPlus":true,"propertyImages":{"images":[{"srcUrl":"https://media.rightmove.co.uk:443/dir/crop/10:9-16:9/79k/78413/78101020/78413_29549408_IMG_01_0000_max_476x317.jpg","url":"79k/78413/78101020/78413_29549408_IMG_01_0000.jpg"}],"mainImageSrc":"https://media.rightmove.co.uk:443/dir/crop/10:9-16:9/79k/78413/78101020/78413_29549408_IMG_01_0000_max_476x317.jpg","mainMapImageSrc":"https://media.rightmove.co.uk:443/dir/crop/10:9-16:9/79k/78413/78101020/78413_29549408_IMG_01_0000_max_296x197.jpg"}}