{"id":92517176,"bedrooms":2,"numberOfImages":9,"numberOfFloorplans":0,"numberOfVirtualTours":0,"summary":"Situated on one of the most sought after streets in it's immediate location Cranford Street has always held a higher regard than surrounding streets. Property is a well proportioned two bedroom and two reception room flat, there is a pleasant kitchen and a neutral family bathroom suite. Exter...","displayAddress":"Cranford Street, South Shields","countryCode":"GB","location":{"latitude":54.976558,"longitude":-1.431525},"propertySubType":"Flat","listingUpdate":{"listingUpdateReason":"new","listingUpdateDate":"2020-05-21T10:14:04Z"},"premiumListing":false,"featuredProperty":false,"price":{"amount":85000,"frequency":"not specified","currencyCode":"GBP","displayPrices":[{"displayPrice":"£85,000","displayPriceQualifier":""}]},"customer":{"branchId":28749,"brandPlusLogoURI":"/company/clogo_23050.jpg","contactTelephone":"0191 687 0387","branchDisplayName":"Andrew Craig, South Shields","branchName":"South Shields","brandTradingName":"Andrew Craig","branchLandingPageUrl":"/estate-agents/agent/Andrew-Craig/South-Shields-28749.html","development":false,"showReducedProperties":true,"commercial":false,"showOnMap":true,"brandPlusLogoUrl":"https://media.rightmove.co.uk:443/dir/company/clogo_23050_max_100x50.jpg"},"distance":null,"transactionType":"buy","productLabel":{"productLabelText":""},"commercial":false,"development":false,"residential":true,"students":false,"auction":false,"feesApply":false,"feesApplyText":null,"displaySize":"","showOnMap":true,"propertyUrl":"/property-for-sale/property-92517176.html","contactUrl":"/property-for-sale/contactBranch.html?propertyId=92517176","channel":"BUY","firstVisibleDate":"2020-05-21T10:08:43Z","keywords":[],"keywordMatchType":"no_keyword","saved":null,"hidden":null,"onlineViewingsAvailable":false,"propertyTypeFullDescription":"2 bedroom flat for sale","propertyImages":{"images":[{"srcUrl":"https://media.rightmove.co.uk:443/dir/crop/10:9-16:9/29k/28749/92517176/28749_380034_IMG_01_0000_max_476x317.jpg","url":"29k/28749/92517176/28749_380034_IMG_01_0000.jpg"},{"srcUrl":"https://media.rightmove.co.uk:443/dir/crop/10:9-16:9/29k/28749/92517176/28749_380034_IMG_02_0000_max_476x317.jpg","url":"29k/28749/92517176/28749_380034_IMG_02_0000.jpg"},{"srcUrl":"https://media.rightmove.co.uk:443/dir/crop/10:9-16:9/29k/28749/92517176/28749_380034_IMG_03_0000_max_476x317.jpg","url":"29k/28749/92517176/28749_380034_IMG_03_0000.jpg"},{"srcUrl":"https://media.rightmove.co.uk:443/dir/crop/10:9-16:9/29k/28749/92517176/28749_380034_IMG_04_0000_max_476x317.jpg","url":"29k/28749/92517176/28749_380034_IMG_04_0000.jpg"},{"srcUrl":"https://media.rightmove.co.uk:443/dir/crop/10:9-16:9/29k/28749/92517176/28749_380034_IMG_05_0000_max_476x317.jpg","url":"29k/28749/92517176/28749_380034_IMG_05_0000.jpg"},{"srcUrl":"https://media.rightmove.co.uk:443/dir/crop/10:9-16:9/29k/28749/92517176/28749_380034_IMG_06_0000_max_476x317.jpg","url":"29k/28749/92517176/28749_380034_IMG_06_0000.jpg"},{"srcUrl":"https://media.rightmove.co.uk:443/dir/crop/10:9-16:9/29k/28749/92517176/28749_380034_IMG_07_0000_max_476x317.jpg","url":"29k/28749/92517176/28749_380034_IMG_07_0000.jpg"},{"srcUrl":"https://media.rightmove.co.uk:443/dir/crop/10:9-16:9/29k/28749/92517176/28749_380034_IMG_08_0000_max_476x317.jpg","url":"29k/28749/92517176/28749_380034_IMG_08_0000.jpg"},{"srcUrl":"https://media.rightmove.co.uk:443/dir/crop/10:9-16:9/29k/28749/92517176/28749_380034_IMG_09_0000_max_476x317.jpg","url":"29k/28749/92517176/28749_380034_IMG_09_0000.jpg"}],"mainImageSrc":"https://media.rightmove.co.uk:443/dir/crop/10:9-16:9/29k/28749/92517176/28749_380034_IMG_01_0000_max_476x317.jpg","mainMapImageSrc":"https://media.rightmove.co.uk:443/dir/crop/10:9-16:9/29k/28749/92517176/28749_380034_IMG_01_0000_max_296x197.jpg"},"displayStatus":"","formattedBranchName":" by Andrew Craig, South Shields","addedOrReduced":"Added on 21/05/2020","isRecent":false,"formattedDistance":"","heading":"","hasBrandPlus":true}