{"id":84645710,"bedrooms":2,"numberOfImages":8,"numberOfFloorplans":1,"numberOfVirtualTours":0,"summary":"Immaculately presented and spacious TWO BEDROOM Apartment on the 7th Floor, in the popular Brayford Pool Area of Lincoln. Consisting of Entrance Hall, Open Plan Lounge/Kitchen/Dining Area, Master Bedroom with Fitted Wardrobes opening on to a balcony and En-Suite, a second Double Bedroom with Fitt...","displayAddress":"Witham Wharf, Lincoln","countryCode":"GB","location":{"latitude":53.227352,"longitude":-0.542676},"propertySubType":"Apartment","listingUpdate":{"listingUpdateReason":"price_reduced","listingUpdateDate":"2020-05-21T14:01:40Z"},"premiumListing":false,"featuredProperty":false,"price":{"amount":189950,"frequency":"not specified","currencyCode":"GBP","displayPrices":[{"displayPrice":"£189,950","displayPriceQualifier":""}]},"customer":{"branchId":83951,"brandPlusLogoURI":"/brand/brand_rmchoice_logo_37774_0008.png","contactTelephone":"01501 511018","branchDisplayName":"Newton Fallowell, Lincoln Sales","branchName":"Lincoln Sales","brandTradingName":"Newton Fallowell","branchLandingPageUrl":"/estate-agents/agent/Newton-Fallowell/Lincoln-Sales-83951.html","development":false,"showReducedProperties":true,"commercial":false,"showOnMap":true,"brandPlusLogoUrl":"https://media.rightmove.co.uk:443/dir/brand/brand_rmchoice_logo_37774_0008_max_100x50.png"},"distance":null,"transactionType":"buy","productLabel":{"productLabelText":""},"commercial":false,"development":false,"residential":true,"students":false,"auction":false,"feesApply":false,"feesApplyText":null,"displaySize":"","showOnMap":true,"propertyUrl":"/property-for-sale/property-84645710.html","contactUrl":"/property-for-sale/contactBranch.html?propertyId=84645710","channel":"BUY","firstVisibleDate":"2019-09-11T09:35:41Z","keywords":[],"keywordMatchType":"no_keyword","saved":null,"hidden":null,"onlineViewingsAvailable":false,"propertyImages":{"images":[{"srcUrl":"https://media.rightmove.co.uk:443/dir/crop/10:9-16:9/84k/83951/84645710/83951_29088969_IMG_01_0000_max_476x317.jpg","url":"84k/83951/84645710/83951_29088969_IMG_01_0000.jpg"},{"srcUrl":"https://media.rightmove.co.uk:443/dir/crop/10:9-16:9/84k/83951/84645710/83951_29088969_IMG_02_0000_max_476x317.jpg","url":"84k/83951/84645710/83951_29088969_IMG_02_0000.jpg"},{"srcUrl":"https://media.rightmove.co.uk:443/dir/crop/10:9-16:9/84k/83951/84645710/83951_29088969_IMG_03_0000_max_476x317.jpg","url":"84k/83951/84645710/83951_29088969_IMG_03_0000.jpg"},{"srcUrl":"https://media.rightmove.co.uk:443/dir/crop/10:9-16:9/84k/83951/84645710/83951_29088969_IMG_04_0000_max_476x317.jpg","url":"84k/83951/84645710/83951_29088969_IMG_04_0000.jpg"},{"srcUrl":"https://media.rightmove.co.uk:443/dir/crop/10:9-16:9/84k/83951/84645710/83951_29088969_IMG_05_0000_max_476x317.jpg","url":"84k/83951/84645710/83951_29088969_IMG_05_0000.jpg"},{"srcUrl":"https://media.rightmove.co.uk:443/dir/crop/10:9-16:9/84k/83951/84645710/83951_29088969_IMG_06_0000_max_476x317.jpg","url":"84k/83951/84645710/83951_29088969_IMG_06_0000.jpg"},{"srcUrl":"https://media.rightmove.co.uk:443/dir/crop/10:9-16:9/84k/83951/84645710/83951_29088969_IMG_07_0000_max_476x317.jpg","url":"84k/83951/84645710/83951_29088969_IMG_07_0000.jpg"},{"srcUrl":"https://media.rightmove.co.uk:443/dir/crop/10:9-16:9/84k/83951/84645710/83951_29088969_IMG_08_0000_max_476x317.jpg","url":"84k/83951/84645710/83951_29088969_IMG_08_0000.jpg"}],"mainImageSrc":"https://media.rightmove.co.uk:443/dir/crop/10:9-16:9/84k/83951/84645710/83951_29088969_IMG_01_0000_max_476x317.jpg","mainMapImageSrc":"https://media.rightmove.co.uk:443/dir/crop/10:9-16:9/84k/83951/84645710/83951_29088969_IMG_01_0000_max_296x197.jpg"},"displayStatus":"","formattedBranchName":" by Newton Fallowell, Lincoln Sales","addedOrReduced":"Reduced on 21/05/2020","isRecent":false,"formattedDistance":"","heading":"","hasBrandPlus":true,"propertyTypeFullDescription":"2 bedroom apartment for sale"}